cantok/__init__.py
cantok/errors.py
cantok/py.typed
cantok/types.py
cantok/tokens/__init__.py
cantok/tokens/condition_token.py
cantok/tokens/counter_token.py
cantok/tokens/default_token.py
cantok/tokens/simple_token.py
cantok/tokens/timeout_token.py
cantok/tokens/abstract/__init__.py
cantok/tokens/abstract/abstract_token.py
cantok/tokens/abstract/cancel_cause.py
cantok/tokens/abstract/coroutine_wrapper.py
cantok/tokens/abstract/report.py
cantok-0.0.32.dist-info/LICENSE
cantok-0.0.32.dist-info/METADATA
cantok-0.0.32.dist-info/WHEEL
cantok-0.0.32.dist-info/top_level.txt
cantok-0.0.32.dist-info/RECORD
