Metadata-Version: 2.1
Name: cantok
Version: 0.0.32
Summary: Implementation of the "Cancellation Token" pattern
Author-email: Evgeniy Blinov <zheni-b@yandex.ru>
Project-URL: Source, https://github.com/pomponchik/cantok
Project-URL: Documentation, http://cantok.readthedocs.io/
Project-URL: Tracker, https://github.com/pomponchik/cantok/issues
Keywords: cancellation tokens,parallel programming,concurrency
Classifier: Operating System :: OS Independent
Classifier: Operating System :: MacOS :: MacOS X
Classifier: Operating System :: Microsoft :: Windows
Classifier: Operating System :: POSIX
Classifier: Operating System :: POSIX :: Linux
Classifier: Programming Language :: Python
Classifier: Programming Language :: Python :: 3.8
Classifier: Programming Language :: Python :: 3.9
Classifier: Programming Language :: Python :: 3.10
Classifier: Programming Language :: Python :: 3.11
Classifier: Programming Language :: Python :: 3.12
Classifier: Programming Language :: Python :: 3.13
Classifier: License :: OSI Approved :: MIT License
Classifier: Intended Audience :: Developers
Classifier: Topic :: Software Development :: Libraries
Requires-Python: >=3.8
License-File: LICENSE
Requires-Dist: displayhooks>=0.0.4
Requires-Dist: typing-extensions; python_version <= "3.9"
